{
  "$schema": "https://raw.githubusercontent.com/microsoft/vcpkg-tool/main/docs/vcpkg.schema.json",
  "name": "tactile",
  "license": "GPL-3.0",
  "version-semver": "0.6.0",
  "maintainers": [
    "albin-johansson"
  ],
  "builtin-baseline": "a54b77790d1632394bc16621ef83613dd4480320",
  "dependencies": [
    "argparse",
    "boost-assert",
    "boost-config",
    "boost-container",
    "boost-dll",
    "boost-predef",
    "boost-stacktrace",
    "boost-uuid",
    "cppcodec",
    "doctest",
    "entt",
    "fmt",
    {
      "name": "glad",
      "features": [
        "extensions"
      ]
    },
    "glm",
    {
      "name": "imgui",
      "features": [
        "docking-experimental",
        "sdl2-binding",
        "opengl3-binding",
        "vulkan-binding"
      ]
    },
    "magic-enum",
    "nlohmann-json",
    "protobuf",
    "pugixml",
    {
      "name": "sdl2",
      "features": [
        "vulkan"
      ]
    },
    "sdl2-image",
    "spdlog",
    "stb",
    "vulkan",
    "vulkan-memory-allocator",
    "tinyfiledialogs",
    "tl-expected",
    "yaml-cpp",
    "zlib",
    "zstd"
  ]
}